create_package_workshop-0.1.1.dist-info/licenses/LICENSE
workshop/__init__.py
workshop/workshop.py
create_package_workshop-0.1.1.dist-info/METADATA
create_package_workshop-0.1.1.dist-info/WHEEL
create_package_workshop-0.1.1.dist-info/top_level.txt
create_package_workshop-0.1.1.dist-info/RECORD
