Metadata-Version: 2.4
Name: create-package-workshop
Version: 0.1.1
Summary: Add your description here
Requires-Python: >=3.10
License-File: LICENSE
Requires-Dist: ipykernel>=6.29.5
Requires-Dist: matplotlib>=3.10.1
Requires-Dist: plotly>=6.0.1
Requires-Dist: scikit-learn>=1.6.1
Requires-Dist: seaborn>=0.13.2
Dynamic: license-file
